[
null,
{"id":1,"expanded":false,"name":"debug","order":15,"parentId":0,"scrollX":982.8,"scrollY":548.4},
{"id":2,"expanded":false,"name":"bedroom","order":1,"parentId":0,"scrollX":1417.2,"scrollY":538.8},
{"id":3,"expanded":true,"name":"Escape Room Entrance","order":5,"parentId":6,"scrollX":1015.1999999999999,"scrollY":538.8},
{"id":4,"expanded":false,"name":"Containment Chamber","order":2,"parentId":0,"scrollX":1053.6,"scrollY":538.8},
{"id":5,"expanded":false,"name":"Van","order":3,"parentId":0,"scrollX":982.8,"scrollY":548.4},
{"id":6,"expanded":true,"name":"Escape Room Interior","order":4,"parentId":0,"scrollX":2640,"scrollY":538.8},
{"id":7,"expanded":false,"name":"multipath","order":6,"parentId":6,"scrollX":1832.3999999999999,"scrollY":700.8},
{"id":8,"expanded":false,"name":"Driving (in my car)","order":8,"parentId":0,"scrollX":982.8,"scrollY":538.8},
{"id":9,"expanded":false,"name":"Porch","order":9,"parentId":0,"scrollX":1786.909090909091,"scrollY":997.0909090909091},
{"id":10,"expanded":true,"name":"Shakelight","order":10,"parentId":0,"scrollX":2679.2727272727275,"scrollY":2201.4545454545455},
{"id":11,"expanded":false,"name":"Trophy","order":7,"parentId":6,"scrollX":982.8,"scrollY":548.4},
{"id":12,"expanded":false,"name":"Shakelight Lanie","order":11,"parentId":10,"scrollX":973.1999999999999,"scrollY":579.6},
{"id":13,"expanded":false,"name":"Credits","order":13,"parentId":0,"scrollX":982.8,"scrollY":548.4},
{"id":14,"expanded":false,"name":"Shakelight Finale","order":12,"parentId":10,"scrollX":982.8,"scrollY":538.8},
{"id":15,"expanded":false,"name":"Front Porch","order":14,"parentId":0,"scrollX":982.8,"scrollY":548.4},
{"id":16,"expanded":false,"name":"Backrooms","order":16,"parentId":0,"scrollX":2070.5454545454545,"scrollY":2860.3636363636365}
]